ais_service_discovery/__init__.py
ais_service_discovery/call_service.py
ais_service_discovery/functions/__init__.py
ais_service_discovery/services/__init__.py
ais_service_discovery/services/cloudmap.py
ais_service_discovery/services/helpers.py
ais_service_discovery/sns/__init__.py
ais_service_discovery/sqs/__init__.py
ais_service_discovery-0.2.0.dist-info/LICENSE
ais_service_discovery-0.2.0.dist-info/METADATA
ais_service_discovery-0.2.0.dist-info/WHEEL
ais_service_discovery-0.2.0.dist-info/top_level.txt
ais_service_discovery-0.2.0.dist-info/RECORD
