Metadata-Version: 2.1
Name: ais-service-discovery
Version: 0.2.0
Summary: AIS service discovery package for python3
Home-page: https://github.com/peak-ai/ais-service-discovery-python
Author: Peak AI
Author-email: infra-notifications@peak.ai
License: UNKNOWN
Keywords: aws service-discovery ais lambda
Platform: UNKNOWN
Classifier: Programming Language :: Python :: 3
Classifier: Operating System :: OS Independent
Requires-Python: >=3.5
Requires-Dist: boto3 (>=1.9.55)
